retrocookie/__init__.py
retrocookie/__main__.py
retrocookie/compat/__init__.py
retrocookie/compat/contextlib.py
retrocookie/core.py
retrocookie/filter.py
retrocookie/git.py
retrocookie/pr/__init__.py
retrocookie/pr/__main__.py
retrocookie/pr/adapters/__init__.py
retrocookie/pr/adapters/github.py
retrocookie/pr/adapters/retrocookie.py
retrocookie/pr/base/__init__.py
retrocookie/pr/base/bus.py
retrocookie/pr/base/exceptionhandlers.py
retrocookie/pr/cache.py
retrocookie/pr/compat/__init__.py
retrocookie/pr/compat/shlex.py
retrocookie/pr/compat/typing.py
retrocookie/pr/console.py
retrocookie/pr/core.py
retrocookie/pr/events.py
retrocookie/pr/importer.py
retrocookie/pr/list.py
retrocookie/pr/protocols/__init__.py
retrocookie/pr/protocols/github.py
retrocookie/pr/protocols/retrocookie.py
retrocookie/pr/repository.py
retrocookie/py.typed
retrocookie/utils.py
retrocookie-0.4.3.dist-info/LICENSE.rst
retrocookie-0.4.3.dist-info/METADATA
retrocookie-0.4.3.dist-info/WHEEL
retrocookie-0.4.3.dist-info/entry_points.txt
retrocookie-0.4.3.dist-info/RECORD
