Metadata-Version: 2.1
Name: retrocookie
Version: 0.4.3
Summary: Update Cookiecutter templates with changes from their instances
Home-page: https://github.com/cjolowicz/retrocookie
License: MIT
Author: Claudio Jolowicz
Author-email: mail@claudiojolowicz.com
Requires-Python: >=3.8.1,<4.0.0
Classifier: Development Status :: 3 - Alpha
Classifier: Environment :: Console
Classifier: Intended Audience :: Developers
Classifier: License :: OSI Approved :: MIT License
Classifier: Operating System :: MacOS
Classifier: Operating System :: Microsoft :: Windows
Classifier: Operating System :: POSIX :: Linux
Classifier: Programming Language :: Python :: 3
Classifier: Programming Language :: Python :: 3.9
Classifier: Programming Language :: Python :: 3.10
Classifier: Programming Language :: Python :: 3.11
Classifier: Programming Language :: Python :: 3.12
Provides-Extra: pr
Requires-Dist: appdirs (>=1.4.4,<2.0.0) ; extra == "pr"
Requires-Dist: click (>=8.0.3,<9.0.0)
Requires-Dist: git-filter-repo (>=2.26.0,<3.0.0)
Requires-Dist: github3.py (>=3.0.0,<4.0.0) ; extra == "pr"
Requires-Dist: pygit2 (>=1.2.1,<1.15)
Requires-Dist: rich (>=9.5.1,<11.0.0) ; extra == "pr"
Requires-Dist: tenacity (>=6.3.1,<9.0.0) ; extra == "pr"
Requires-Dist: typing-extensions (>=3.7.4,<5.0.0) ; extra == "pr"
Project-URL: Changelog, https://github.com/cjolowicz/retrocookie/releases
Project-URL: Documentation, https://retrocookie.readthedocs.io
Project-URL: Repository, https://github.com/cjolowicz/retrocookie
